opush.py
opush-1.0.4.dist-info/LICENSE
opush-1.0.4.dist-info/METADATA
opush-1.0.4.dist-info/WHEEL
opush-1.0.4.dist-info/top_level.txt
opush-1.0.4.dist-info/RECORD
