Metadata-Version: 2.1
Name: opush
Version: 1.0.4
Summary: Push message to your devices and social accounts easily.
Home-page: UNKNOWN
Author: UNKNOWN
Author-email: UNKNOWN
License: UNKNOWN
Platform: UNKNOWN
